FHmonitor/FHmonitor_main.py
FHmonitor/__init__.py
FHmonitor/atm90_e32_pi.py
FHmonitor/atm90_e32_registers.py
FHmonitor/error_handling.py
FHmonitor/monitor.py
FHmonitor/store.py
FHmonitor-0.0.6.dist-info/AUTHORS.rst
FHmonitor-0.0.6.dist-info/LICENSE
FHmonitor-0.0.6.dist-info/METADATA
FHmonitor-0.0.6.dist-info/WHEEL
FHmonitor-0.0.6.dist-info/entry_points.txt
FHmonitor-0.0.6.dist-info/top_level.txt
FHmonitor-0.0.6.dist-info/RECORD
