Metadata-Version: 2.1
Name: FHmonitor
Version: 0.0.6
Summary: Reads and stores the atm90e32 power values.
Home-page: https://github.com/bitknitting/FHmonitor
Author: Margaret Johnson
Author-email: contact@fithome.life
License: MIT license
Keywords: FHmonitor
Platform: UNKNOWN
Classifier: Development Status :: 2 - Pre-Alpha
Classifier: Intended Audience :: Developers
Classifier: License :: OSI Approved :: MIT License
Classifier: Natural Language :: English
Classifier: Programming Language :: Python :: 3
Classifier: Programming Language :: Python :: 3.5
Classifier: Programming Language :: Python :: 3.6
Classifier: Programming Language :: Python :: 3.7
Classifier: Programming Language :: Python :: 3.8
Requires-Python: >=3.5
Requires-Dist: pymongo (==3.4.0)
Requires-Dist: Adafruit-Blinka (==4.1.0)
Requires-Dist: adafruit-circuitpython-busdevice (==4.2.1)
